DZDutils/__init__.py
DZDutils/dict.py
DZDutils/files.py
DZDutils/list.py
DZDutils/inspect/__init__.py
DZDutils/inspect/get_full_class_name.py
DZDutils/inspect/html_template.html.template
DZDutils/inspect/object2html.py
DZDutils/neo4j/FullTextIndexBucketMultiProcessor.py
DZDutils/neo4j/LuceneTextCleanerTools.py
DZDutils/neo4j/TextIndexBucketProcessor.py
DZDutils/neo4j/__init__.py
DZDutils/neo4j/tools/__init__.py
DZDutils/neo4j/tools/nodes_to_buckets_distributor.py
DZDutils/neo4j/tools/run_periodic_iterate.py
DZDutils/neo4j/tools/wait_for_db_boot.py
DZDutils/neo4j/tools/wait_for_index_build_up.py
DZDutils-1.7.4.dist-info/LICENSE.md
DZDutils-1.7.4.dist-info/METADATA
DZDutils-1.7.4.dist-info/WHEEL
DZDutils-1.7.4.dist-info/top_level.txt
DZDutils-1.7.4.dist-info/RECORD
