Metadata-Version: 2.1
Name: DZDutils
Version: 1.7.4
Summary: Tool collection from the DZD Devs
Home-page: https://git.connect.dzd-ev.de/dzdpythonmodules/dzdutils
Author: TB
Author-email: tim.bleimehl@helmholtz-muenchen.de
License: MIT
Requires-Python: >=3.6
License-File: LICENSE.md
Requires-Dist: py2neo
Requires-Dist: numpy
Requires-Dist: linetimer
Requires-Dist: graphio
Requires-Dist: pandas
